giwime/__init__.py
giwime/cli.py
giwime/status.py
git_withme-25.10.0.dist-info/METADATA
git_withme-25.10.0.dist-info/WHEEL
git_withme-25.10.0.dist-info/entry_points.txt
git_withme-25.10.0.dist-info/licenses/LICENSE
git_withme-25.10.0.dist-info/RECORD
