Metadata-Version: 2.4
Name: git-withme
Version: 25.10.0
Summary: Encrypted, peer-to-peer Git for two+ people.
Project-URL: Homepage, https://sr.ht/~meejah/git-withme/
Project-URL: Repository, https://git.sr.ht/~meejah/git-withme
Project-URL: Issues, https://todo.sr.ht/~meejah/git-withme
Author-email: meejah <meejah@meejah.ca>
License: The MIT License (MIT)
License-File: LICENSE
Keywords: cryptography,infosec,magic-wormhole,privacy
Classifier: Framework :: Twisted
Classifier: License :: OSI Approved :: MIT License
Classifier: Programming Language :: Python :: 3
Requires-Python: >=3.6
Requires-Dist: click
Requires-Dist: fowl
Requires-Dist: humanize
Requires-Dist: magic-wormhole
Requires-Dist: rich
Provides-Extra: dev
Requires-Dist: cuvner; extra == 'dev'
Requires-Dist: dulwich; extra == 'dev'
Requires-Dist: gpg; extra == 'dev'
Requires-Dist: hatch; extra == 'dev'
Requires-Dist: pip-tools; extra == 'dev'
Requires-Dist: readme-renderer; extra == 'dev'
Requires-Dist: sphinx; extra == 'dev'
Requires-Dist: twine; extra == 'dev'
Provides-Extra: test
Requires-Dist: pytest; extra == 'test'
